monocular/__init__.py
monocular/api.py
monocular/background_subtractors.py
monocular/config.py
monocular/data_buckets.py
monocular/databuckets.py
monocular/detectors.py
monocular/face_identifiers.py
monocular/images.py
monocular/util.py
monocular/tests/__init__.py
monocular/tests/test_monocular.py
monocular-1.1.0.dist-info/DESCRIPTION.rst
monocular-1.1.0.dist-info/METADATA
monocular-1.1.0.dist-info/RECORD
monocular-1.1.0.dist-info/WHEEL
monocular-1.1.0.dist-info/metadata.json
monocular-1.1.0.dist-info/top_level.txt
