Metadata-Version: 2.0
Name: monocular
Version: 1.1.0
Summary: The Monocular SDK provides access to the Jemsoft Monocular API.
Home-page: http://docs.jemsoft.co
Author: Jemsoft Pty Ltd
Author-email: hello@jemsoft.co
License: Jemsoft Monocular Python SDK - Terms and conditions
Requires-Dist: Pillow
Requires-Dist: requests
